galaxy_ng/__init__.py
galaxy_ng/_vendor/__init__.py
galaxy_ng/_vendor/automated_logging/__init__.py
galaxy_ng/_vendor/automated_logging/apps.py
galaxy_ng/_vendor/automated_logging/decorators.py
galaxy_ng/_vendor/automated_logging/handlers.py
galaxy_ng/_vendor/automated_logging/middleware.py
galaxy_ng/_vendor/automated_logging/models.py
galaxy_ng/_vendor/automated_logging/settings.py
galaxy_ng/_vendor/automated_logging/urls.py
galaxy_ng/_vendor/automated_logging/views.py
galaxy_ng/_vendor/automated_logging/admin/__init__.py
galaxy_ng/_vendor/automated_logging/admin/base.py
galaxy_ng/_vendor/automated_logging/admin/model_entry.py
galaxy_ng/_vendor/automated_logging/admin/model_event.py
galaxy_ng/_vendor/automated_logging/admin/model_mirror.py
galaxy_ng/_vendor/automated_logging/admin/request_event.py
galaxy_ng/_vendor/automated_logging/admin/unspecified_event.py
galaxy_ng/_vendor/automated_logging/helpers/__init__.py
galaxy_ng/_vendor/automated_logging/helpers/enums.py
galaxy_ng/_vendor/automated_logging/helpers/exceptions.py
galaxy_ng/_vendor/automated_logging/helpers/schemas.py
galaxy_ng/_vendor/automated_logging/migrations/0001_initial.py
galaxy_ng/_vendor/automated_logging/migrations/0002_auto_20180215_1540.py
galaxy_ng/_vendor/automated_logging/migrations/0003_auto_20180216_0900.py
galaxy_ng/_vendor/automated_logging/migrations/0004_auto_20180216_0935.py
galaxy_ng/_vendor/automated_logging/migrations/0005_auto_20180216_0941.py
galaxy_ng/_vendor/automated_logging/migrations/0006_auto_20180216_1004.py
galaxy_ng/_vendor/automated_logging/migrations/0007_auto_20180216_1005.py
galaxy_ng/_vendor/automated_logging/migrations/0008_auto_20180216_1005.py
galaxy_ng/_vendor/automated_logging/migrations/0009_auto_20180216_1006.py
galaxy_ng/_vendor/automated_logging/migrations/0010_auto_20180216_1430.py
galaxy_ng/_vendor/automated_logging/migrations/0011_auto_20180216_1545.py
galaxy_ng/_vendor/automated_logging/migrations/0012_auto_20180218_1101.py
galaxy_ng-4.9.2.dist-info/LICENSE
galaxy_ng-4.9.2.dist-info/METADATA
galaxy_ng-4.9.2.dist-info/WHEEL
galaxy_ng-4.9.2.dist-info/entry_points.txt
galaxy_ng-4.9.2.dist-info/top_level.txt
galaxy_ng-4.9.2.dist-info/RECORD
