Metadata-Version: 2.1
Name: galaxy-ng
Version: 4.9.2
Summary: galaxy-ng plugin for the Pulp Project
Home-page: https://github.com/ansible/galaxy_ng/
Author: Red Hat, Inc.
Author-email: info@ansible.com
License: GPLv2+
Platform: UNKNOWN
Classifier: License :: OSI Approved :: GNU General Public License v2 or later (GPLv2+)
Classifier: Operating System :: POSIX :: Linux
Classifier: Framework :: Django
Classifier: Programming Language :: Python
Classifier: Programming Language :: Python :: 3
Classifier: Programming Language :: Python :: 3.8
Classifier: Programming Language :: Python :: 3.9
Requires-Python: >=3.8
License-File: LICENSE
Requires-Dist: boto3
Requires-Dist: distro
Requires-Dist: django-auth-ldap (==4.0.0)
Requires-Dist: django-ipware (<4.0.0,>=3.0.0)
Requires-Dist: django-picklefield (<4.0.0,>=3.0.1)
Requires-Dist: django-prometheus (>=2.0.0)
Requires-Dist: drf-spectacular
Requires-Dist: dynaconf (<3.1.13,>=3.1.12)
Requires-Dist: galaxy-importer (<=0.4.19,>=0.4.16)
Requires-Dist: insights-analytics-collector (>=0.3.0)
Requires-Dist: marshmallow (<4.0.0,>=3.6.1)
Requires-Dist: pulp-container (<2.16.0,>=2.15.0)
Requires-Dist: pulp-ansible (<0.21.0,>=0.20.3)
Requires-Dist: pulpcore (<3.29.0,>=3.28.21)
Requires-Dist: setuptools (<66)
Requires-Dist: social-auth-app-django (>=5.2.0)
Requires-Dist: social-auth-core (>=4.4.2)
Requires-Dist: backports.zoneinfo (==0.2.1) ; python_version < "3.9"
